{% extends "base.xml" %}

{% block root %}
<trials>
{% for trial in trial_list %}
    <trial>
        <main>
            <trial_id>{{ trial.ct_fossil.trial_id }}</trial_id>
            <utrn>{{ trial.ct_fossil.utrn_number }}</utrn>
            <reg_name>{{ reg_name }}</reg_name>
            <date_registration>{{ trial.ct_fossil.date_registration|date:"d/m/Y" }}</date_registration>
            <primary_sponsor>{{ trial.primary_sponsor }}</primary_sponsor>
            <public_title>{{ trial.ct_fossil.public_title }}</public_title>
            <acronym>{{ trial.ct_fossil.acronym_display }}</acronym>
            <scientific_title>{{ trial.ct_fossil.scientific_title }}</scientific_title>
            <scientific_acronym>{{ trial.ct_fossil.scientific_acronym_display }}</scientific_acronym>
            <date_enrolment>{{ trial.ct_fossil.date_enrollment_start }}</date_enrolment>
            <type_enrolment>{% if trial.ct_fossil.enrollment_start_actual %}actual{% else %}anticipated{% endif %}</type_enrolment>
            <target_size>{{ trial.ct_fossil.target_sample_size }}</target_size>
            <recruitment_status>{{ trial.ct_fossil.recruitment_status.label }}</recruitment_status>
            <url>{% url repository.trial_registered_version trial_fossil_id=trial.ct_fossil.trial_id, trial_version=trial.version %}</url>
            <study_type>{{ trial.ct_fossil.study_type.label }}</study_type>
            <study_design>{{ trial.ct_fossil.study_design }}</study_design>
            <phase>{{ trial.ct_fossil.phase.label }}</phase>
            <hc_freetext>{{ trial.ct_fossil.hc_freetext }}</hc_freetext>
            <i_freetext>{{ trial.ct_fossil.i_freetext }}</i_freetext>            
        </main>
        <contacts>
        {% for contact in trial.public_contact %}
            <contact>
                <type>public</type>
                <firstname>{{ contact.firstname }}</firstname>
                <middlename>{{ contact.middlename }}</middlename>
                <lastname>{{ contact.lastname }}</lastname>
                <address>{{ contact.address }}</address>
                <city>{{ contact.city }}</city>
                <country1>{{ contact.country.description }}</country1>
                <zip>{{ contact.zip }}</zip>
                <telephone>{{ contact.telephone }}</telephone>
                <email>{{ contact.email }}</email>
                <affiliation>{{ contact.affiliation.name }}</affiliation>
            </contact>
        {% endfor %}
        {% for contact in trial.ct_fossil.scientific_contact %}
            <contact>
                <type>scientific</type>
                <firstname>{{ contact.firstname }}</firstname>
                <middlename>{{ contact.middlename }}</middlename>
                <lastname>{{ contact.lastname }}</lastname>
                <address>{{ contact.address }}</address>
                <city>{{ contact.city }}</city>
                <country1>{{ contact.country.description }}</country1>
                <zip>{{ contact.zip }}</zip>
                <telephone>{{ contact.telephone }}</telephone>
                <email>{{ contact.email }}</email>
                <affiliation>{{ contact.affiliation.name }}</affiliation>
            </contact>
        {% endfor %}
        </contacts>
        <countries>
        {% for country in trial.ct_fossil.recruitment_country %}
            <country2>{{ country.description }}</country2>
        {% endfor %}
        </countries>
        <criteria>
            <inclusion_criteria>{{ trial.ct_fossil.inclusion_criteria }}</inclusion_criteria>
            <agemin>{{ trial.ct_fossil.agemin_value }}{% if trial.ct_fossil.agemin_unit != '-' %}{{ trial.ct_fossil.agemin_unit }}{% endif %}</agemin>
            <agemax>{{ trial.ct_fossil.agemax_value }}{% if trial.ct_fossil.agemax_unit != '-' %}{{ trial.ct_fossil.agemax_unit }}{% endif %}</agemax>
            <gender>{{ trial.ct_fossil.gender }}</gender>
            <exclusion_criteria>{{ trial.ct_fossil.exclusion_criteria }}</exclusion_criteria>
        </criteria>
        <health_condition_code>
            {% for hc in trial.ct_fossil.hc_code %}
            <hc_code>{{ hc.code }}</hc_code>
            {% endfor %}
        </health_condition_code>
        <health_condition_keyword>
            {% for hc in trial.ct_fossil.hc_keyword %}
            <hc_keyword>{{ hc.code }}</hc_keyword>
            {% endfor %}
        </health_condition_keyword>
        <intervention_code>
            {% for iv in trial.ct_fossil.i_code %}
            <i_code>{{ iv.label }}</i_code>
            {% endfor %}
        </intervention_code>
        <intervention_keyword>
            {% for iv in trial.ct_fossil.intervention_keyword %}
            <i_keyword>{{ iv.code }}</i_keyword>
            {% endfor %}
        </intervention_keyword>
        <primary_outcome>
            {% for outcomes in trial.ct_fossil.primary_outcomes %}
            <prim_outcome>{{ outcomes.description }}</prim_outcome>
            {% endfor %}
        </primary_outcome>
        <secondary_outcome>
            {% for outcomes in trial.ct_fossil.secondary_outcomes %}
            <sec_outcome>{{ outcomes.description }}</sec_outcome>
            {% empty %}
            <sec_outcome></sec_outcome>
            {% endfor %}
        </secondary_outcome>
        <secondary_sponsor>
            {%  for sponsor in trial.secondary_sponsors %}
            <sponsor_name>{{ sponsor }}</sponsor_name>
            {% empty %}
            <sponsor_name></sponsor_name>
            {% endfor %}
        </secondary_sponsor>
        <secondary_ids>
            {% for secid in trial.ct_fossil.trial_number %}
            <secondary_id>
                <sec_id>{{ secid.id_number }}</sec_id>
                <issuing_authority>{{ secid.issuing_authority }}</issuing_authority>    
            </secondary_id>
            {% empty %}
            <secondary_id>
                <sec_id></sec_id>
                <issuing_authority></issuing_authority>    
            </secondary_id>
            {% endfor %}
        </secondary_ids>
        <source_support>
            {%  for source in trial.source_support %}
            <source_name>{{ source }}</source_name>
            {% empty %}
            <source_name></source_name>
            {% endfor %}
        </source_support>        
    </trial>
{% endfor %}
</trials>
{% endblock %}